{
  "pipa": "Glitch Wraith",
  "a52sxq": "Genoxci",
  "vili": "0mar",
  "violet": "Selfmuser",
  "Spacewar": "DaViDev985",
  "a71": "DaViDev985",
  "beyond0lte": "DaViDev985",
  "beyond1lte": "DaViDev985",
  "beyond2lte": "DaViDev985",
  "toco": "Dennis Murimi (AndroidHQ254)",
  "raphael": "Arghaya Mondal (ergdev)", 
  "bluejay": "Einar Gednochsson", 
  "oriole": "Einar Gednochsson", 
  "raven": "Einar Gednochsson", 
  "zippo": "Einar Gednochsson",
  "vayu": "Bagaskara",
  "Pong": "Semina Alexandru(NeiKos496)"
}
